{
  "title": "Classic (GV Flavor)",
  "phases": [
    {
      "title": "Understand",
      "end_time": "4:00pm",
      "exercise": [
        {
          "title": "Introduction",
          "time": "10:00am"
        },
        {
          "title": "Problem Statement",
          "time": "10:15am",
          "slug": "problem-statement"
        },
        {
          "title": "Sprint Questions",
          "time": "10:35am",
          "slug": "sprint-questions"
        },
        {
          "title": "Break",
          "time": "11:00am"
        },
        {
          "title": "Make a Map",
          "time": "11:15am",
          "slug": "make-a-map"
        },
        {
          "title": "Ask the Experts: Slot 1",
          "time": "12:00pm",
          "slug": "ask-the-experts"
        },
        {
          "title": "Break",
          "time": "1:00pm"
        },
        {
          "title": "Ask the Experts: Slot 2",
          "time": "2:00pm",
          "slug": "ask-the-experts"
        },
        {
          "title": "Card Sorting",
          "time": "3:00pm",
          "slug": "card-sorting"
        },
        {
          "title": "Pick a Target",
          "time": "3:30pm",
          "slug": "pick-a-target"
        },
        {
          "title": "Optional",
          "divider": true
        },
        {
          "slug": "assumptions-board",
          "title": "Start an assumptions board"
        },
        {
          "slug": "backburner-board",
          "title": "Start a backburner board"
        }
      ]
    },
    {
      "title": "Diverge",
      "end_time": "4:00pm",
      "exercise": [
        {
          "title": "Recap",
          "time": "10:00am"
        },
        {
          "title": "Lightning Demos",
          "time": "10:30am",
          "slug": "lightning-demos"
        },
        {
          "title": "Break",
          "time": "11:30am"
        },
        {
          "title": "Four-Step Sketch: Session 1",
          "time": "11:45am",
          "slug": "four-step-sketches"
        },
        {
          "title": "Break",
          "time": "12:45pm"
        },
        {
          "title": "Four-Step Sketch: Session 2",
          "time": "1:45pm",
          "slug": "four-step-sketches"
        },
        {
          "title": "Break",
          "time": "2:45pm"
        },
        {
          "title": "Four-Step Sketch: Session 3",
          "time": "3:00pm",
          "slug": "four-step-sketches"
        }
      ]
    },
    {
      "title": "Converge",
      "end_time": "4:00pm",
      "exercise": [
        {
          "title": "Recap",
          "time": "10:00am"
        },
        {
          "title": "Art Gallery",
          "time": "10:30am",
          "slug": "art-museum"
        },
        {
          "title": "Break",
          "time": "12:30pm"
        },
        {
          "title": "Final Storyboard (with Breaks)",
          "time": "1:30pm",
          "slug": "final-storyboard"
        }
      ]
    },
    {
      "title": "Prototype",
      "exercise": [
        {
          "title": "Build the prototype",
          "time": "All Day"
        },
        {
          "title": "Write the script",
          "time": "All Day"
        }
      ]
    },
    {
      "title": "Test",
      "exercise": [
        {
          "title": "Test the prototype",
          "time": "All Day"
        }
      ]
    }
  ]
}